[{"name": "KOSPI", "current_value": "643,656.00", "value": "643,656.00", "change_rate": -0.61, "changeRate": -0.61, "status": "down", "is_outlier": false, "message": "\uc804\uc77c \ub300\ube44 \uc548\uc815\uc801 \ud750\ub984 \uc720\uc9c0", "validated_at": "2026-04-24 03:49"}, {"name": "KOSDAQ", "current_value": "119,859.00", "value": "119,859.00", "change_rate": 2.07, "changeRate": 2.07, "status": "up", "is_outlier": false, "message": "\uc804\uc77c \ub300\ube44 \uc548\uc815\uc801 \ud750\ub984 \uc720\uc9c0", "validated_at": "2026-04-24 03:49"}]